DirectoryCleaner-0.3.data/data/LICENSE.txt
DirectoryCleaner-0.3.data/data/README.md
DirectoryCleaner-0.3.dist-info/METADATA
DirectoryCleaner-0.3.dist-info/RECORD
DirectoryCleaner-0.3.dist-info/WHEEL
DirectoryCleaner-0.3.dist-info/entry_points.txt
DirectoryCleaner-0.3.dist-info/top_level.txt
directorycleaner/__init__.py
directorycleaner/color_print.py
directorycleaner/directory_cleaner.py
directorycleaner/main.py
directorycleaner/regex.py
directorycleaner/settings.py
directorycleaner/data/extensions.json
directorycleaner/scripts/populate.py
directorycleaner/scripts/scraper.py
directorycleaner/tests/test_general.py
