Metadata-Version: 2.1
Name: DirectoryCleaner
Version: 0.3
Summary: An easy to use program that will clean a specified directory by placing all loose files in one folder with specified sub folders.
Home-page: https://github.com/Cantasaurus/DirectoryCleaner
Author: Danny Canter
Author-email: dannycanter123@gmail.com
License: MIT
Platform: UNKNOWN
Provides-Extra: Scraper
Requires-Dist: tqdm (>=4.25.0)
Requires-Dist: pyfiglet (>=0.7.5)
Provides-Extra: Scraper
Requires-Dist: beautifulsoup4 (>=4.6.3); extra == 'Scraper'
Requires-Dist: requests (>=2.19.1); extra == 'Scraper'
